grpc_invoke/__init__.py
grpc_invoke/grpc_client.py
grpc_invoke/gexceptions/MethodException.py
grpc_invoke/gexceptions/ParamsException.py
grpc_invoke/gexceptions/ServiceException.py
grpc_invoke/gexceptions/__init__.py
grpc_invoke/reflection_grpc/__init__.py
grpc_invoke/reflection_grpc/descriptor_cache.py
grpc_invoke/reflection_grpc/reflection.py
grpc_invoke/reflection_grpc/reflection_stub.py
grpc_invoke-0.0.13.dist-info/LICENSE
grpc_invoke-0.0.13.dist-info/METADATA
grpc_invoke-0.0.13.dist-info/WHEEL
grpc_invoke-0.0.13.dist-info/top_level.txt
grpc_invoke-0.0.13.dist-info/RECORD
