Metadata-Version: 2.1
Name: grpc-invoke
Version: 0.0.13
Summary: a grpc request tool like requests
Home-page: https://github.com/wuranxu/grpc-invoke
Author: woody(吴冉旭)
Author-email: 619434176@qq.com
License: UNKNOWN
Platform: UNKNOWN
Classifier: Programming Language :: Python :: 3
Classifier: License :: OSI Approved :: MIT License
Classifier: Operating System :: OS Independent
License-File: LICENSE
